<?xml version="1.0" encoding="utf-8"?>
<Data numAnimations="1">
  <Animation>
    <Image numFrames="4">
      <Path>EnemySprites/overworldobjects.png</Path>
    </Image>
    <Looping>True</Looping>
    <Name>Overworld</Name>
    <NextName>None</NextName>
    <Frame delay="0.15">
      <AnchorPoint x="16" y="395" />
      <DrawRect left="3" top="386" right="29" bottom="418" />
      <CollisionRect left="0" top="0" right="0" bottom="0" />
      <Event>NoEvent</Event>
    </Frame>
    <Frame delay="0.15">
      <AnchorPoint x="48" y="395" />
      <DrawRect left="34" top="385" right="61" bottom="418" />
      <CollisionRect left="0" top="0" right="0" bottom="0" />
      <Event>NoEvent</Event>
    </Frame>
    <Frame delay="0.15">
      <AnchorPoint x="80" y="395" />
      <DrawRect left="65" top="385" right="94" bottom="418" />
      <CollisionRect left="0" top="0" right="0" bottom="0" />
      <Event>NoEvent</Event>
    </Frame>
    <Frame delay="0.15">
      <AnchorPoint x="48" y="395" />
      <DrawRect left="37" top="386" right="60" bottom="419" />
      <CollisionRect left="0" top="0" right="0" bottom="0" />
      <Event>NoEvent</Event>
    </Frame>
  </Animation>
</Data>