<?xml version="1.0" encoding="utf-8"?>
<Data numAnimations="1">
  <Animation>
    <Image numFrames="3">
      <Path>Tailor.png</Path>
    </Image>
    <Looping>True</Looping>
    <Name>Timeline</Name>
    <NextName>none</NextName>
    <Frame delay="0.15">
      <AnchorPoint x="278" y="590" />
      <DrawRect left="256" top="576" right="303" bottom="643" />
      <CollisionRect left="0" top="0" right="0" bottom="0" />
      <Event>NoEvent</Event>
    </Frame>
    <Frame delay="0.15">
      <AnchorPoint x="337" y="590" />
      <DrawRect left="317" top="573" right="357" bottom="640" />
      <CollisionRect left="0" top="0" right="0" bottom="0" />
      <Event>NoEvent</Event>
    </Frame>
    <Frame delay="0.25">
      <AnchorPoint x="397" y="590" />
      <DrawRect left="377" top="576" right="436" bottom="635" />
      <CollisionRect left="0" top="0" right="0" bottom="0" />
      <Event>NoEvent</Event>
    </Frame>
  </Animation>
</Data>